{
  "$collection": "color",
  "$mode": "light",
  "variables": [
    {
      "name": "color/background/primary",
      "resolvedType": "COLOR",
      "scopes": [
        "FRAME_FILL",
        "SHAPE_FILL"
      ],
      "description": "",
      "value": {
        "r": 0.9137254953384399,
        "g": 0.9137254953384399,
        "b": 0.9176470637321472,
        "a": 1
      },
      "alias": {
        "type": "VARIABLE_ALIAS",
        "name": "palette/neutral/050"
      }
    },
    {
      "name": "color/background/secondary",
      "resolvedType": "COLOR",
      "scopes": [
        "FRAME_FILL",
        "SHAPE_FILL"
      ],
      "description": "",
      "value": {
        "r": 0.8588235378265381,
        "g": 0.8588235378265381,
        "b": 0.8666666746139526,
        "a": 1
      },
      "alias": {
        "type": "VARIABLE_ALIAS",
        "name": "palette/neutral/100"
      }
    },
    {
      "name": "color/background/tertiary",
      "resolvedType": "COLOR",
      "scopes": [
        "FRAME_FILL",
        "SHAPE_FILL"
      ],
      "description": "",
      "value": {
        "r": 0.8078431487083435,
        "g": 0.8078431487083435,
        "b": 0.8156862854957581,
        "a": 1
      },
      "alias": {
        "type": "VARIABLE_ALIAS",
        "name": "palette/neutral/150"
      }
    },
    {
      "name": "color/background/inverse/primary",
      "resolvedType": "COLOR",
      "scopes": [
        "FRAME_FILL",
        "SHAPE_FILL"
      ],
      "description": "",
      "value": {
        "r": 0.05098039284348488,
        "g": 0.05098039284348488,
        "b": 0.054901961237192154,
        "a": 1
      },
      "alias": {
        "type": "VARIABLE_ALIAS",
        "name": "palette/neutral/950"
      }
    },
    {
      "name": "color/background/inverse/secondary",
      "resolvedType": "COLOR",
      "scopes": [
        "FRAME_FILL",
        "SHAPE_FILL"
      ],
      "description": "",
      "value": {
        "r": 0.09019608050584793,
        "g": 0.09019608050584793,
        "b": 0.09803921729326248,
        "a": 1
      },
      "alias": {
        "type": "VARIABLE_ALIAS",
        "name": "palette/neutral/900"
      }
    },
    {
      "name": "color/background/inverse/tertiary",
      "resolvedType": "COLOR",
      "scopes": [
        "FRAME_FILL",
        "SHAPE_FILL"
      ],
      "description": "",
      "value": {
        "r": 0.12941177189350128,
        "g": 0.12941177189350128,
        "b": 0.1411764770746231,
        "a": 1
      },
      "alias": {
        "type": "VARIABLE_ALIAS",
        "name": "palette/neutral/850"
      }
    },
    {
      "name": "color/scrim/default",
      "resolvedType": "COLOR",
      "scopes": [
        "FRAME_FILL",
        "SHAPE_FILL"
      ],
      "description": "",
      "value": {
        "r": 0,
        "g": 0,
        "b": 0,
        "a": 1
      },
      "alias": {
        "type": "VARIABLE_ALIAS",
        "name": "palette/black-alpha/40"
      }
    },
    {
      "name": "color/foreground/primary",
      "resolvedType": "COLOR",
      "scopes": [
        "FRAME_FILL",
        "SHAPE_FILL",
        "TEXT_FILL"
      ],
      "description": "",
      "value": {
        "r": 0.8588235378265381,
        "g": 0.8588235378265381,
        "b": 0.8666666746139526,
        "a": 1
      },
      "alias": {
        "type": "VARIABLE_ALIAS",
        "name": "palette/neutral/100"
      }
    },
    {
      "name": "color/foreground/secondary",
      "resolvedType": "COLOR",
      "scopes": [
        "FRAME_FILL",
        "SHAPE_FILL",
        "TEXT_FILL"
      ],
      "description": "",
      "value": {
        "r": 0.8078431487083435,
        "g": 0.8078431487083435,
        "b": 0.8156862854957581,
        "a": 1
      },
      "alias": {
        "type": "VARIABLE_ALIAS",
        "name": "palette/neutral/150"
      }
    },
    {
      "name": "color/foreground/tertiary",
      "resolvedType": "COLOR",
      "scopes": [
        "FRAME_FILL",
        "SHAPE_FILL",
        "TEXT_FILL"
      ],
      "description": "",
      "value": {
        "r": 0.7568627595901489,
        "g": 0.7568627595901489,
        "b": 0.7647058963775635,
        "a": 1
      },
      "alias": {
        "type": "VARIABLE_ALIAS",
        "name": "palette/neutral/200"
      }
    },
    {
      "name": "color/foreground/inverse/primary",
      "resolvedType": "COLOR",
      "scopes": [
        "FRAME_FILL",
        "SHAPE_FILL",
        "TEXT_FILL"
      ],
      "description": "",
      "value": {
        "r": 0.09019608050584793,
        "g": 0.09019608050584793,
        "b": 0.09803921729326248,
        "a": 1
      },
      "alias": {
        "type": "VARIABLE_ALIAS",
        "name": "palette/neutral/900"
      }
    },
    {
      "name": "color/foreground/inverse/secondary",
      "resolvedType": "COLOR",
      "scopes": [
        "FRAME_FILL",
        "SHAPE_FILL",
        "TEXT_FILL"
      ],
      "description": "",
      "value": {
        "r": 0.12941177189350128,
        "g": 0.12941177189350128,
        "b": 0.1411764770746231,
        "a": 1
      },
      "alias": {
        "type": "VARIABLE_ALIAS",
        "name": "palette/neutral/850"
      }
    },
    {
      "name": "color/foreground/inverse/tertiary",
      "resolvedType": "COLOR",
      "scopes": [
        "FRAME_FILL",
        "SHAPE_FILL",
        "TEXT_FILL"
      ],
      "description": "",
      "value": {
        "r": 0.1725490242242813,
        "g": 0.1725490242242813,
        "b": 0.18431372940540314,
        "a": 1
      },
      "alias": {
        "type": "VARIABLE_ALIAS",
        "name": "palette/neutral/800"
      }
    },
    {
      "name": "color/foreground/brand",
      "resolvedType": "COLOR",
      "scopes": [
        "FRAME_FILL",
        "SHAPE_FILL",
        "TEXT_FILL"
      ],
      "description": "",
      "value": {
        "r": 0.3686274588108063,
        "g": 0.29411765933036804,
        "b": 0.7647058963775635,
        "a": 1
      },
      "alias": {
        "type": "VARIABLE_ALIAS",
        "name": "palette/primary/550"
      }
    },
    {
      "name": "color/foreground/success",
      "resolvedType": "COLOR",
      "scopes": [
        "FRAME_FILL",
        "SHAPE_FILL",
        "TEXT_FILL"
      ],
      "description": "",
      "value": {
        "r": 0.18431372940540314,
        "g": 0.40784314274787903,
        "b": 0.20000000298023224,
        "a": 1
      },
      "alias": {
        "type": "VARIABLE_ALIAS",
        "name": "palette/success/600"
      }
    },
    {
      "name": "color/foreground/warning",
      "resolvedType": "COLOR",
      "scopes": [
        "FRAME_FILL",
        "SHAPE_FILL",
        "TEXT_FILL"
      ],
      "description": "",
      "value": {
        "r": 0.4941176474094391,
        "g": 0.32549020648002625,
        "b": 0,
        "a": 1
      },
      "alias": {
        "type": "VARIABLE_ALIAS",
        "name": "palette/warning/600"
      }
    },
    {
      "name": "color/foreground/info",
      "resolvedType": "COLOR",
      "scopes": [
        "FRAME_FILL",
        "SHAPE_FILL",
        "TEXT_FILL"
      ],
      "description": "",
      "value": {
        "r": 0.12156862765550613,
        "g": 0.3764705955982208,
        "b": 0.5647059082984924,
        "a": 1
      },
      "alias": {
        "type": "VARIABLE_ALIAS",
        "name": "palette/info/600"
      }
    },
    {
      "name": "color/foreground/brand-subtle",
      "resolvedType": "COLOR",
      "scopes": [
        "FRAME_FILL",
        "SHAPE_FILL",
        "TEXT_FILL"
      ],
      "description": "",
      "value": {
        "r": 0.8549019694328308,
        "g": 0.8549019694328308,
        "b": 0.929411768913269,
        "a": 1
      },
      "alias": {
        "type": "VARIABLE_ALIAS",
        "name": "palette/primary/100"
      }
    },
    {
      "name": "color/foreground/success-subtle",
      "resolvedType": "COLOR",
      "scopes": [
        "FRAME_FILL",
        "SHAPE_FILL",
        "TEXT_FILL"
      ],
      "description": "",
      "value": {
        "r": 0.6705882549285889,
        "g": 0.9372549057006836,
        "b": 0.6745098233222961,
        "a": 1
      },
      "alias": {
        "type": "VARIABLE_ALIAS",
        "name": "palette/success/100"
      }
    },
    {
      "name": "color/foreground/warning-subtle",
      "resolvedType": "COLOR",
      "scopes": [
        "FRAME_FILL",
        "SHAPE_FILL",
        "TEXT_FILL"
      ],
      "description": "",
      "value": {
        "r": 0.95686274766922,
        "g": 0.843137264251709,
        "b": 0.6901960968971252,
        "a": 1
      },
      "alias": {
        "type": "VARIABLE_ALIAS",
        "name": "palette/warning/100"
      }
    },
    {
      "name": "color/foreground/danger-subtle",
      "resolvedType": "COLOR",
      "scopes": [
        "FRAME_FILL",
        "SHAPE_FILL",
        "TEXT_FILL"
      ],
      "description": "",
      "value": {
        "r": 0.9490196108818054,
        "g": 0.8352941274642944,
        "b": 0.8235294222831726,
        "a": 1
      },
      "alias": {
        "type": "VARIABLE_ALIAS",
        "name": "palette/danger/100"
      }
    },
    {
      "name": "color/foreground/info-subtle",
      "resolvedType": "COLOR",
      "scopes": [
        "FRAME_FILL",
        "SHAPE_FILL",
        "TEXT_FILL"
      ],
      "description": "",
      "value": {
        "r": 0.7960784435272217,
        "g": 0.8705882430076599,
        "b": 0.9372549057006836,
        "a": 1
      },
      "alias": {
        "type": "VARIABLE_ALIAS",
        "name": "palette/info/100"
      }
    },
    {
      "name": "color/foreground/danger/default",
      "resolvedType": "COLOR",
      "scopes": [
        "FRAME_FILL",
        "SHAPE_FILL",
        "TEXT_FILL"
      ],
      "description": "",
      "value": {
        "r": 0.6313725709915161,
        "g": 0.21568627655506134,
        "b": 0.1921568661928177,
        "a": 1
      },
      "alias": {
        "type": "VARIABLE_ALIAS",
        "name": "palette/danger/600"
      }
    },
    {
      "name": "color/foreground/danger/hover",
      "resolvedType": "COLOR",
      "scopes": [
        "FRAME_FILL",
        "SHAPE_FILL",
        "TEXT_FILL"
      ],
      "description": "",
      "value": {
        "r": 0.5568627715110779,
        "g": 0.1764705926179886,
        "b": 0.15294118225574493,
        "a": 1
      },
      "alias": {
        "type": "VARIABLE_ALIAS",
        "name": "palette/danger/650"
      }
    },
    {
      "name": "color/foreground/danger/pressed",
      "resolvedType": "COLOR",
      "scopes": [
        "FRAME_FILL",
        "SHAPE_FILL",
        "TEXT_FILL"
      ],
      "description": "",
      "value": {
        "r": 0.48235294222831726,
        "g": 0.13725490868091583,
        "b": 0.12156862765550613,
        "a": 1
      },
      "alias": {
        "type": "VARIABLE_ALIAS",
        "name": "palette/danger/700"
      }
    },
    {
      "name": "color/foreground/danger/focused",
      "resolvedType": "COLOR",
      "scopes": [
        "FRAME_FILL",
        "SHAPE_FILL",
        "TEXT_FILL"
      ],
      "description": "",
      "value": {
        "r": 0.5568627715110779,
        "g": 0.1764705926179886,
        "b": 0.15294118225574493,
        "a": 1
      },
      "alias": {
        "type": "VARIABLE_ALIAS",
        "name": "palette/danger/650"
      }
    },
    {
      "name": "color/foreground/danger/selected",
      "resolvedType": "COLOR",
      "scopes": [
        "FRAME_FILL",
        "SHAPE_FILL",
        "TEXT_FILL"
      ],
      "description": "",
      "value": {
        "r": 0.48235294222831726,
        "g": 0.13725490868091583,
        "b": 0.12156862765550613,
        "a": 1
      },
      "alias": {
        "type": "VARIABLE_ALIAS",
        "name": "palette/danger/700"
      }
    },
    {
      "name": "color/foreground/danger/disabled",
      "resolvedType": "COLOR",
      "scopes": [
        "FRAME_FILL",
        "SHAPE_FILL",
        "TEXT_FILL"
      ],
      "description": "",
      "value": {
        "r": 0.7568627595901489,
        "g": 0.7568627595901489,
        "b": 0.7647058963775635,
        "a": 1
      },
      "alias": {
        "type": "VARIABLE_ALIAS",
        "name": "palette/neutral/200"
      }
    },
    {
      "name": "color/action/default",
      "resolvedType": "COLOR",
      "scopes": [
        "FRAME_FILL",
        "SHAPE_FILL",
        "STROKE_COLOR"
      ],
      "description": "",
      "value": {
        "r": 0,
        "g": 0.3803921639919281,
        "b": 0.5333333611488342,
        "a": 1
      },
      "alias": {
        "type": "VARIABLE_ALIAS",
        "name": "palette/accent/600"
      }
    },
    {
      "name": "color/action/hover",
      "resolvedType": "COLOR",
      "scopes": [
        "FRAME_FILL",
        "SHAPE_FILL",
        "STROKE_COLOR"
      ],
      "description": "",
      "value": {
        "r": 0,
        "g": 0.3294117748737335,
        "b": 0.4627451002597809,
        "a": 1
      },
      "alias": {
        "type": "VARIABLE_ALIAS",
        "name": "palette/accent/650"
      }
    },
    {
      "name": "color/action/pressed",
      "resolvedType": "COLOR",
      "scopes": [
        "FRAME_FILL",
        "SHAPE_FILL",
        "STROKE_COLOR"
      ],
      "description": "",
      "value": {
        "r": 0,
        "g": 0.27843138575553894,
        "b": 0.4000000059604645,
        "a": 1
      },
      "alias": {
        "type": "VARIABLE_ALIAS",
        "name": "palette/accent/700"
      }
    },
    {
      "name": "color/action/focused",
      "resolvedType": "COLOR",
      "scopes": [
        "FRAME_FILL",
        "SHAPE_FILL",
        "STROKE_COLOR"
      ],
      "description": "",
      "value": {
        "r": 0,
        "g": 0.3294117748737335,
        "b": 0.4627451002597809,
        "a": 1
      },
      "alias": {
        "type": "VARIABLE_ALIAS",
        "name": "palette/accent/650"
      }
    },
    {
      "name": "color/action/selected",
      "resolvedType": "COLOR",
      "scopes": [
        "FRAME_FILL",
        "SHAPE_FILL",
        "STROKE_COLOR"
      ],
      "description": "",
      "value": {
        "r": 0,
        "g": 0.27843138575553894,
        "b": 0.4000000059604645,
        "a": 1
      },
      "alias": {
        "type": "VARIABLE_ALIAS",
        "name": "palette/accent/700"
      }
    },
    {
      "name": "color/action/disabled",
      "resolvedType": "COLOR",
      "scopes": [
        "FRAME_FILL",
        "SHAPE_FILL",
        "STROKE_COLOR"
      ],
      "description": "",
      "value": {
        "r": 0.7568627595901489,
        "g": 0.7568627595901489,
        "b": 0.7647058963775635,
        "a": 1
      },
      "alias": {
        "type": "VARIABLE_ALIAS",
        "name": "palette/neutral/200"
      }
    },
    {
      "name": "color/text/primary",
      "resolvedType": "COLOR",
      "scopes": [
        "TEXT_FILL"
      ],
      "description": "",
      "value": {
        "r": 0.05098039284348488,
        "g": 0.05098039284348488,
        "b": 0.054901961237192154,
        "a": 1
      },
      "alias": {
        "type": "VARIABLE_ALIAS",
        "name": "palette/neutral/950"
      }
    },
    {
      "name": "color/text/secondary",
      "resolvedType": "COLOR",
      "scopes": [
        "TEXT_FILL"
      ],
      "description": "",
      "value": {
        "r": 0.3607843220233917,
        "g": 0.3607843220233917,
        "b": 0.3803921639919281,
        "a": 1
      },
      "alias": {
        "type": "VARIABLE_ALIAS",
        "name": "palette/neutral/600"
      }
    },
    {
      "name": "color/text/tertiary",
      "resolvedType": "COLOR",
      "scopes": [
        "TEXT_FILL"
      ],
      "description": "",
      "value": {
        "r": 0.4588235318660736,
        "g": 0.4627451002597809,
        "b": 0.47843137383461,
        "a": 1
      },
      "alias": {
        "type": "VARIABLE_ALIAS",
        "name": "palette/neutral/500"
      }
    },
    {
      "name": "color/text/disabled",
      "resolvedType": "COLOR",
      "scopes": [
        "TEXT_FILL"
      ],
      "description": "",
      "value": {
        "r": 0.4588235318660736,
        "g": 0.4627451002597809,
        "b": 0.47843137383461,
        "a": 1
      },
      "alias": {
        "type": "VARIABLE_ALIAS",
        "name": "palette/neutral/500"
      }
    },
    {
      "name": "color/text/brand",
      "resolvedType": "COLOR",
      "scopes": [
        "TEXT_FILL"
      ],
      "description": "",
      "value": {
        "r": 0.3686274588108063,
        "g": 0.29411765933036804,
        "b": 0.7647058963775635,
        "a": 1
      },
      "alias": {
        "type": "VARIABLE_ALIAS",
        "name": "palette/primary/550"
      }
    },
    {
      "name": "color/text/success",
      "resolvedType": "COLOR",
      "scopes": [
        "TEXT_FILL"
      ],
      "description": "",
      "value": {
        "r": 0.18431372940540314,
        "g": 0.40784314274787903,
        "b": 0.20000000298023224,
        "a": 1
      },
      "alias": {
        "type": "VARIABLE_ALIAS",
        "name": "palette/success/600"
      }
    },
    {
      "name": "color/text/warning",
      "resolvedType": "COLOR",
      "scopes": [
        "TEXT_FILL"
      ],
      "description": "",
      "value": {
        "r": 0.4941176474094391,
        "g": 0.32549020648002625,
        "b": 0,
        "a": 1
      },
      "alias": {
        "type": "VARIABLE_ALIAS",
        "name": "palette/warning/600"
      }
    },
    {
      "name": "color/text/danger",
      "resolvedType": "COLOR",
      "scopes": [
        "TEXT_FILL"
      ],
      "description": "",
      "value": {
        "r": 0.6313725709915161,
        "g": 0.21568627655506134,
        "b": 0.1921568661928177,
        "a": 1
      },
      "alias": {
        "type": "VARIABLE_ALIAS",
        "name": "palette/danger/600"
      }
    },
    {
      "name": "color/text/info",
      "resolvedType": "COLOR",
      "scopes": [
        "TEXT_FILL"
      ],
      "description": "",
      "value": {
        "r": 0.12156862765550613,
        "g": 0.3764705955982208,
        "b": 0.5647059082984924,
        "a": 1
      },
      "alias": {
        "type": "VARIABLE_ALIAS",
        "name": "palette/info/600"
      }
    },
    {
      "name": "color/text/brand-subtle",
      "resolvedType": "COLOR",
      "scopes": [
        "TEXT_FILL"
      ],
      "description": "",
      "value": {
        "r": 0.4901960790157318,
        "g": 0.46666666865348816,
        "b": 0.8078431487083435,
        "a": 1
      },
      "alias": {
        "type": "VARIABLE_ALIAS",
        "name": "palette/primary/450"
      }
    },
    {
      "name": "color/text/success-subtle",
      "resolvedType": "COLOR",
      "scopes": [
        "TEXT_FILL"
      ],
      "description": "",
      "value": {
        "r": 0.3019607961177826,
        "g": 0.5686274766921997,
        "b": 0.3176470696926117,
        "a": 1
      },
      "alias": {
        "type": "VARIABLE_ALIAS",
        "name": "palette/success/450"
      }
    },
    {
      "name": "color/text/warning-subtle",
      "resolvedType": "COLOR",
      "scopes": [
        "TEXT_FILL"
      ],
      "description": "",
      "value": {
        "r": 0.6823529601097107,
        "g": 0.4627451002597809,
        "b": 0.05098039284348488,
        "a": 1
      },
      "alias": {
        "type": "VARIABLE_ALIAS",
        "name": "palette/warning/450"
      }
    },
    {
      "name": "color/text/danger-subtle",
      "resolvedType": "COLOR",
      "scopes": [
        "TEXT_FILL"
      ],
      "description": "",
      "value": {
        "r": 0.8509804010391235,
        "g": 0.3333333432674408,
        "b": 0.2980392277240753,
        "a": 1
      },
      "alias": {
        "type": "VARIABLE_ALIAS",
        "name": "palette/danger/450"
      }
    },
    {
      "name": "color/text/info-subtle",
      "resolvedType": "COLOR",
      "scopes": [
        "TEXT_FILL"
      ],
      "description": "",
      "value": {
        "r": 0.22745098173618317,
        "g": 0.529411792755127,
        "b": 0.7647058963775635,
        "a": 1
      },
      "alias": {
        "type": "VARIABLE_ALIAS",
        "name": "palette/info/450"
      }
    },
    {
      "name": "color/text/on-action",
      "resolvedType": "COLOR",
      "scopes": [
        "TEXT_FILL"
      ],
      "description": "",
      "value": {
        "r": 1,
        "g": 1,
        "b": 1,
        "a": 1
      },
      "alias": {
        "type": "VARIABLE_ALIAS",
        "name": "palette/white"
      }
    },
    {
      "name": "color/text/on-brand",
      "resolvedType": "COLOR",
      "scopes": [
        "TEXT_FILL"
      ],
      "description": "",
      "value": {
        "r": 1,
        "g": 1,
        "b": 1,
        "a": 1
      },
      "alias": {
        "type": "VARIABLE_ALIAS",
        "name": "palette/white"
      }
    },
    {
      "name": "color/text/on-success",
      "resolvedType": "COLOR",
      "scopes": [
        "TEXT_FILL"
      ],
      "description": "",
      "value": {
        "r": 1,
        "g": 1,
        "b": 1,
        "a": 1
      },
      "alias": {
        "type": "VARIABLE_ALIAS",
        "name": "palette/white"
      }
    },
    {
      "name": "color/text/on-warning",
      "resolvedType": "COLOR",
      "scopes": [
        "TEXT_FILL"
      ],
      "description": "",
      "value": {
        "r": 1,
        "g": 1,
        "b": 1,
        "a": 1
      },
      "alias": {
        "type": "VARIABLE_ALIAS",
        "name": "palette/white"
      }
    },
    {
      "name": "color/text/on-danger",
      "resolvedType": "COLOR",
      "scopes": [
        "TEXT_FILL"
      ],
      "description": "",
      "value": {
        "r": 1,
        "g": 1,
        "b": 1,
        "a": 1
      },
      "alias": {
        "type": "VARIABLE_ALIAS",
        "name": "palette/white"
      }
    },
    {
      "name": "color/text/on-info",
      "resolvedType": "COLOR",
      "scopes": [
        "TEXT_FILL"
      ],
      "description": "",
      "value": {
        "r": 1,
        "g": 1,
        "b": 1,
        "a": 1
      },
      "alias": {
        "type": "VARIABLE_ALIAS",
        "name": "palette/white"
      }
    },
    {
      "name": "color/text/on-inverse",
      "resolvedType": "COLOR",
      "scopes": [
        "TEXT_FILL"
      ],
      "description": "",
      "value": {
        "r": 0.9686274528503418,
        "g": 0.9686274528503418,
        "b": 0.9686274528503418,
        "a": 1
      },
      "alias": {
        "type": "VARIABLE_ALIAS",
        "name": "palette/neutral/025"
      }
    },
    {
      "name": "color/text/on-disabled",
      "resolvedType": "COLOR",
      "scopes": [
        "TEXT_FILL"
      ],
      "description": "",
      "value": {
        "r": 0.40784314274787903,
        "g": 0.40784314274787903,
        "b": 0.4274509847164154,
        "a": 1
      },
      "alias": {
        "type": "VARIABLE_ALIAS",
        "name": "palette/neutral/550"
      }
    },
    {
      "name": "color/text/link/default",
      "resolvedType": "COLOR",
      "scopes": [
        "TEXT_FILL"
      ],
      "description": "",
      "value": {
        "r": 0,
        "g": 0.3803921639919281,
        "b": 0.5333333611488342,
        "a": 1
      },
      "alias": {
        "type": "VARIABLE_ALIAS",
        "name": "palette/accent/600"
      }
    },
    {
      "name": "color/text/link/hover",
      "resolvedType": "COLOR",
      "scopes": [
        "TEXT_FILL"
      ],
      "description": "",
      "value": {
        "r": 0,
        "g": 0.3294117748737335,
        "b": 0.4627451002597809,
        "a": 1
      },
      "alias": {
        "type": "VARIABLE_ALIAS",
        "name": "palette/accent/650"
      }
    },
    {
      "name": "color/text/link/visited",
      "resolvedType": "COLOR",
      "scopes": [
        "TEXT_FILL"
      ],
      "description": "",
      "value": {
        "r": 0,
        "g": 0.27843138575553894,
        "b": 0.4000000059604645,
        "a": 1
      },
      "alias": {
        "type": "VARIABLE_ALIAS",
        "name": "palette/accent/700"
      }
    },
    {
      "name": "color/text/link/focused",
      "resolvedType": "COLOR",
      "scopes": [
        "TEXT_FILL"
      ],
      "description": "",
      "value": {
        "r": 0,
        "g": 0.3803921639919281,
        "b": 0.5333333611488342,
        "a": 1
      },
      "alias": {
        "type": "VARIABLE_ALIAS",
        "name": "palette/accent/600"
      }
    },
    {
      "name": "color/icon/primary",
      "resolvedType": "COLOR",
      "scopes": [
        "FRAME_FILL",
        "SHAPE_FILL",
        "STROKE_COLOR"
      ],
      "description": "",
      "value": {
        "r": 0.05098039284348488,
        "g": 0.05098039284348488,
        "b": 0.054901961237192154,
        "a": 1
      },
      "alias": {
        "type": "VARIABLE_ALIAS",
        "name": "palette/neutral/950"
      }
    },
    {
      "name": "color/icon/secondary",
      "resolvedType": "COLOR",
      "scopes": [
        "FRAME_FILL",
        "SHAPE_FILL",
        "STROKE_COLOR"
      ],
      "description": "",
      "value": {
        "r": 0.4588235318660736,
        "g": 0.4627451002597809,
        "b": 0.47843137383461,
        "a": 1
      },
      "alias": {
        "type": "VARIABLE_ALIAS",
        "name": "palette/neutral/500"
      }
    },
    {
      "name": "color/icon/tertiary",
      "resolvedType": "COLOR",
      "scopes": [
        "FRAME_FILL",
        "SHAPE_FILL",
        "STROKE_COLOR"
      ],
      "description": "",
      "value": {
        "r": 0.4588235318660736,
        "g": 0.4627451002597809,
        "b": 0.47843137383461,
        "a": 1
      },
      "alias": {
        "type": "VARIABLE_ALIAS",
        "name": "palette/neutral/500"
      }
    },
    {
      "name": "color/icon/disabled",
      "resolvedType": "COLOR",
      "scopes": [
        "FRAME_FILL",
        "SHAPE_FILL",
        "STROKE_COLOR"
      ],
      "description": "",
      "value": {
        "r": 0.4588235318660736,
        "g": 0.4627451002597809,
        "b": 0.47843137383461,
        "a": 1
      },
      "alias": {
        "type": "VARIABLE_ALIAS",
        "name": "palette/neutral/500"
      }
    },
    {
      "name": "color/icon/brand",
      "resolvedType": "COLOR",
      "scopes": [
        "FRAME_FILL",
        "SHAPE_FILL",
        "STROKE_COLOR"
      ],
      "description": "",
      "value": {
        "r": 0.3686274588108063,
        "g": 0.29411765933036804,
        "b": 0.7647058963775635,
        "a": 1
      },
      "alias": {
        "type": "VARIABLE_ALIAS",
        "name": "palette/primary/550"
      }
    },
    {
      "name": "color/icon/success",
      "resolvedType": "COLOR",
      "scopes": [
        "FRAME_FILL",
        "SHAPE_FILL",
        "STROKE_COLOR"
      ],
      "description": "",
      "value": {
        "r": 0.26274511218070984,
        "g": 0.5137255191802979,
        "b": 0.27843138575553894,
        "a": 1
      },
      "alias": {
        "type": "VARIABLE_ALIAS",
        "name": "palette/success/500"
      }
    },
    {
      "name": "color/icon/warning",
      "resolvedType": "COLOR",
      "scopes": [
        "FRAME_FILL",
        "SHAPE_FILL",
        "STROKE_COLOR"
      ],
      "description": "",
      "value": {
        "r": 0.6235294342041016,
        "g": 0.41960784792900085,
        "b": 0,
        "a": 1
      },
      "alias": {
        "type": "VARIABLE_ALIAS",
        "name": "palette/warning/500"
      }
    },
    {
      "name": "color/icon/danger",
      "resolvedType": "COLOR",
      "scopes": [
        "FRAME_FILL",
        "SHAPE_FILL",
        "STROKE_COLOR"
      ],
      "description": "",
      "value": {
        "r": 0.7882353067398071,
        "g": 0.2980392277240753,
        "b": 0.2666666805744171,
        "a": 1
      },
      "alias": {
        "type": "VARIABLE_ALIAS",
        "name": "palette/danger/500"
      }
    },
    {
      "name": "color/icon/info",
      "resolvedType": "COLOR",
      "scopes": [
        "FRAME_FILL",
        "SHAPE_FILL",
        "STROKE_COLOR"
      ],
      "description": "",
      "value": {
        "r": 0.1921568661928177,
        "g": 0.48235294222831726,
        "b": 0.6980392336845398,
        "a": 1
      },
      "alias": {
        "type": "VARIABLE_ALIAS",
        "name": "palette/info/500"
      }
    },
    {
      "name": "color/icon/brand-subtle",
      "resolvedType": "COLOR",
      "scopes": [
        "FRAME_FILL",
        "SHAPE_FILL",
        "STROKE_COLOR"
      ],
      "description": "",
      "value": {
        "r": 0.4901960790157318,
        "g": 0.46666666865348816,
        "b": 0.8078431487083435,
        "a": 1
      },
      "alias": {
        "type": "VARIABLE_ALIAS",
        "name": "palette/primary/450"
      }
    },
    {
      "name": "color/icon/success-subtle",
      "resolvedType": "COLOR",
      "scopes": [
        "FRAME_FILL",
        "SHAPE_FILL",
        "STROKE_COLOR"
      ],
      "description": "",
      "value": {
        "r": 0.3019607961177826,
        "g": 0.5686274766921997,
        "b": 0.3176470696926117,
        "a": 1
      },
      "alias": {
        "type": "VARIABLE_ALIAS",
        "name": "palette/success/450"
      }
    },
    {
      "name": "color/icon/warning-subtle",
      "resolvedType": "COLOR",
      "scopes": [
        "FRAME_FILL",
        "SHAPE_FILL",
        "STROKE_COLOR"
      ],
      "description": "",
      "value": {
        "r": 0.6823529601097107,
        "g": 0.4627451002597809,
        "b": 0.05098039284348488,
        "a": 1
      },
      "alias": {
        "type": "VARIABLE_ALIAS",
        "name": "palette/warning/450"
      }
    },
    {
      "name": "color/icon/danger-subtle",
      "resolvedType": "COLOR",
      "scopes": [
        "FRAME_FILL",
        "SHAPE_FILL",
        "STROKE_COLOR"
      ],
      "description": "",
      "value": {
        "r": 0.8509804010391235,
        "g": 0.3333333432674408,
        "b": 0.2980392277240753,
        "a": 1
      },
      "alias": {
        "type": "VARIABLE_ALIAS",
        "name": "palette/danger/450"
      }
    },
    {
      "name": "color/icon/info-subtle",
      "resolvedType": "COLOR",
      "scopes": [
        "FRAME_FILL",
        "SHAPE_FILL",
        "STROKE_COLOR"
      ],
      "description": "",
      "value": {
        "r": 0.22745098173618317,
        "g": 0.529411792755127,
        "b": 0.7647058963775635,
        "a": 1
      },
      "alias": {
        "type": "VARIABLE_ALIAS",
        "name": "palette/info/450"
      }
    },
    {
      "name": "color/icon/on-action",
      "resolvedType": "COLOR",
      "scopes": [
        "FRAME_FILL",
        "SHAPE_FILL",
        "STROKE_COLOR"
      ],
      "description": "",
      "value": {
        "r": 1,
        "g": 1,
        "b": 1,
        "a": 1
      },
      "alias": {
        "type": "VARIABLE_ALIAS",
        "name": "palette/white"
      }
    },
    {
      "name": "color/icon/on-brand",
      "resolvedType": "COLOR",
      "scopes": [
        "FRAME_FILL",
        "SHAPE_FILL",
        "STROKE_COLOR"
      ],
      "description": "",
      "value": {
        "r": 1,
        "g": 1,
        "b": 1,
        "a": 1
      },
      "alias": {
        "type": "VARIABLE_ALIAS",
        "name": "palette/white"
      }
    },
    {
      "name": "color/icon/on-success",
      "resolvedType": "COLOR",
      "scopes": [
        "FRAME_FILL",
        "SHAPE_FILL",
        "STROKE_COLOR"
      ],
      "description": "",
      "value": {
        "r": 1,
        "g": 1,
        "b": 1,
        "a": 1
      },
      "alias": {
        "type": "VARIABLE_ALIAS",
        "name": "palette/white"
      }
    },
    {
      "name": "color/icon/on-warning",
      "resolvedType": "COLOR",
      "scopes": [
        "FRAME_FILL",
        "SHAPE_FILL",
        "STROKE_COLOR"
      ],
      "description": "",
      "value": {
        "r": 1,
        "g": 1,
        "b": 1,
        "a": 1
      },
      "alias": {
        "type": "VARIABLE_ALIAS",
        "name": "palette/white"
      }
    },
    {
      "name": "color/icon/on-danger",
      "resolvedType": "COLOR",
      "scopes": [
        "FRAME_FILL",
        "SHAPE_FILL",
        "STROKE_COLOR"
      ],
      "description": "",
      "value": {
        "r": 1,
        "g": 1,
        "b": 1,
        "a": 1
      },
      "alias": {
        "type": "VARIABLE_ALIAS",
        "name": "palette/white"
      }
    },
    {
      "name": "color/icon/on-info",
      "resolvedType": "COLOR",
      "scopes": [
        "FRAME_FILL",
        "SHAPE_FILL",
        "STROKE_COLOR"
      ],
      "description": "",
      "value": {
        "r": 1,
        "g": 1,
        "b": 1,
        "a": 1
      },
      "alias": {
        "type": "VARIABLE_ALIAS",
        "name": "palette/white"
      }
    },
    {
      "name": "color/icon/on-inverse",
      "resolvedType": "COLOR",
      "scopes": [
        "FRAME_FILL",
        "SHAPE_FILL",
        "STROKE_COLOR"
      ],
      "description": "",
      "value": {
        "r": 0.9686274528503418,
        "g": 0.9686274528503418,
        "b": 0.9686274528503418,
        "a": 1
      },
      "alias": {
        "type": "VARIABLE_ALIAS",
        "name": "palette/neutral/025"
      }
    },
    {
      "name": "color/icon/on-disabled",
      "resolvedType": "COLOR",
      "scopes": [
        "FRAME_FILL",
        "SHAPE_FILL",
        "STROKE_COLOR"
      ],
      "description": "",
      "value": {
        "r": 0.40784314274787903,
        "g": 0.40784314274787903,
        "b": 0.4274509847164154,
        "a": 1
      },
      "alias": {
        "type": "VARIABLE_ALIAS",
        "name": "palette/neutral/550"
      }
    },
    {
      "name": "color/icon/link/default",
      "resolvedType": "COLOR",
      "scopes": [
        "FRAME_FILL",
        "SHAPE_FILL",
        "STROKE_COLOR"
      ],
      "description": "",
      "value": {
        "r": 0,
        "g": 0.3803921639919281,
        "b": 0.5333333611488342,
        "a": 1
      },
      "alias": {
        "type": "VARIABLE_ALIAS",
        "name": "palette/accent/600"
      }
    },
    {
      "name": "color/icon/link/hover",
      "resolvedType": "COLOR",
      "scopes": [
        "FRAME_FILL",
        "SHAPE_FILL",
        "STROKE_COLOR"
      ],
      "description": "",
      "value": {
        "r": 0,
        "g": 0.3294117748737335,
        "b": 0.4627451002597809,
        "a": 1
      },
      "alias": {
        "type": "VARIABLE_ALIAS",
        "name": "palette/accent/650"
      }
    },
    {
      "name": "color/icon/link/visited",
      "resolvedType": "COLOR",
      "scopes": [
        "FRAME_FILL",
        "SHAPE_FILL",
        "STROKE_COLOR"
      ],
      "description": "",
      "value": {
        "r": 0,
        "g": 0.27843138575553894,
        "b": 0.4000000059604645,
        "a": 1
      },
      "alias": {
        "type": "VARIABLE_ALIAS",
        "name": "palette/accent/700"
      }
    },
    {
      "name": "color/icon/link/focused",
      "resolvedType": "COLOR",
      "scopes": [
        "FRAME_FILL",
        "SHAPE_FILL",
        "STROKE_COLOR"
      ],
      "description": "",
      "value": {
        "r": 0,
        "g": 0.3803921639919281,
        "b": 0.5333333611488342,
        "a": 1
      },
      "alias": {
        "type": "VARIABLE_ALIAS",
        "name": "palette/accent/600"
      }
    },
    {
      "name": "color/border/primary",
      "resolvedType": "COLOR",
      "scopes": [
        "STROKE_COLOR"
      ],
      "description": "",
      "value": {
        "r": 0.7568627595901489,
        "g": 0.7568627595901489,
        "b": 0.7647058963775635,
        "a": 1
      },
      "alias": {
        "type": "VARIABLE_ALIAS",
        "name": "palette/neutral/200"
      }
    },
    {
      "name": "color/border/secondary",
      "resolvedType": "COLOR",
      "scopes": [
        "STROKE_COLOR"
      ],
      "description": "",
      "value": {
        "r": 0.5058823823928833,
        "g": 0.5098039507865906,
        "b": 0.5254902243614197,
        "a": 1
      },
      "alias": {
        "type": "VARIABLE_ALIAS",
        "name": "palette/neutral/450"
      }
    },
    {
      "name": "color/border/inverse",
      "resolvedType": "COLOR",
      "scopes": [
        "STROKE_COLOR"
      ],
      "description": "",
      "value": {
        "r": 0.1725490242242813,
        "g": 0.1725490242242813,
        "b": 0.18431372940540314,
        "a": 1
      },
      "alias": {
        "type": "VARIABLE_ALIAS",
        "name": "palette/neutral/800"
      }
    },
    {
      "name": "color/border/brand",
      "resolvedType": "COLOR",
      "scopes": [
        "STROKE_COLOR"
      ],
      "description": "",
      "value": {
        "r": 0.4470588266849518,
        "g": 0.4117647111415863,
        "b": 0.7921568751335144,
        "a": 1
      },
      "alias": {
        "type": "VARIABLE_ALIAS",
        "name": "palette/primary/500"
      }
    },
    {
      "name": "color/border/success",
      "resolvedType": "COLOR",
      "scopes": [
        "STROKE_COLOR"
      ],
      "description": "",
      "value": {
        "r": 0.26274511218070984,
        "g": 0.5137255191802979,
        "b": 0.27843138575553894,
        "a": 1
      },
      "alias": {
        "type": "VARIABLE_ALIAS",
        "name": "palette/success/500"
      }
    },
    {
      "name": "color/border/warning",
      "resolvedType": "COLOR",
      "scopes": [
        "STROKE_COLOR"
      ],
      "description": "",
      "value": {
        "r": 0.6235294342041016,
        "g": 0.41960784792900085,
        "b": 0,
        "a": 1
      },
      "alias": {
        "type": "VARIABLE_ALIAS",
        "name": "palette/warning/500"
      }
    },
    {
      "name": "color/border/danger",
      "resolvedType": "COLOR",
      "scopes": [
        "STROKE_COLOR"
      ],
      "description": "",
      "value": {
        "r": 0.7882353067398071,
        "g": 0.2980392277240753,
        "b": 0.2666666805744171,
        "a": 1
      },
      "alias": {
        "type": "VARIABLE_ALIAS",
        "name": "palette/danger/500"
      }
    },
    {
      "name": "color/border/info",
      "resolvedType": "COLOR",
      "scopes": [
        "STROKE_COLOR"
      ],
      "description": "",
      "value": {
        "r": 0.1921568661928177,
        "g": 0.48235294222831726,
        "b": 0.6980392336845398,
        "a": 1
      },
      "alias": {
        "type": "VARIABLE_ALIAS",
        "name": "palette/info/500"
      }
    },
    {
      "name": "color/border/focus",
      "resolvedType": "COLOR",
      "scopes": [
        "STROKE_COLOR"
      ],
      "description": "",
      "value": {
        "r": 0,
        "g": 0.3803921639919281,
        "b": 0.5333333611488342,
        "a": 1
      },
      "alias": {
        "type": "VARIABLE_ALIAS",
        "name": "palette/accent/600"
      }
    }
  ]
}
